postcell/__init__.py
postcell/postcell.py
postcell-0.1.4.dist-info/METADATA
postcell-0.1.4.dist-info/WHEEL
postcell-0.1.4.dist-info/top_level.txt
postcell-0.1.4.dist-info/RECORD
