Metadata-Version: 2.1
Name: postcell
Version: 0.1.4
Summary: Jupyter magic to post content of cells to postcell.io
Home-page: https://postcell.io
Author: Shahbaz Chaudhary
Author-email: shahbazc@gmail.com
License: UNKNOWN
Platform: UNKNOWN
Classifier: Programming Language :: Python :: 3
Classifier: Operating System :: OS Independent
Requires-Python: >=3.6
Requires-Dist: requests
Requires-Dist: ipython
Requires-Dist: jupyter
